macwinnie_py_pushover_client/Pushover.py
macwinnie_py_pushover_client/__init__.py
macwinnie_py_pushover_client/db_migrations/20220913_01_zLEIt-create-table-messages.py
macwinnie_py_pushover_client-2.0.5.dist-info/LICENSE
macwinnie_py_pushover_client-2.0.5.dist-info/METADATA
macwinnie_py_pushover_client-2.0.5.dist-info/WHEEL
macwinnie_py_pushover_client-2.0.5.dist-info/RECORD
