Metadata-Version: 2.3
Name: macwinnie-py-pushover-client
Version: 2.0.5
Summary: Pushover client for Python projects.
License: GNU AFFERO GENERAL PUBLIC LICENSE
Author: macwinnie
Author-email: dev@macwinnie.me
Requires-Python: >=3.11,<4
Classifier: License :: OSI Approved :: GNU Affero General Public License v3 or later (AGPLv3+)
Classifier: License :: Other/Proprietary License
Classifier: Operating System :: OS Independent
Classifier: Programming Language :: Python :: 3
Classifier: Programming Language :: Python :: 3.11
Classifier: Programming Language :: Python :: 3.12
Classifier: Programming Language :: Python :: 3.13
Requires-Dist: macwinnie-pyhelpers (>=3.0.0,<4.0.0)
Requires-Dist: macwinnie-sqlite3 (>=1.0.2,<2.0.0)
Project-URL: Homepage, https://macwinnie.github.io/python-pushover/
Project-URL: Repository, https://github.com/macwinnie/python-pushover/
